Metadata-Version: 2.1
Name: spotycli
Version: 0.3.1
Author: micheledinelli
Author-email: dinellimichele00@gmail.com
License-File: LICENSE
